fsm.v
module fsm (
    input  wire clk,
    input  wire reset,
    output reg  red,
    output reg  green,
    output reg  yellow
);
parameter RED_STATE    = 2'b00;
parameter GREEN_STATE  = 2'b10;
parameter YELLOW_STATE = 2'b01;
parameter RED_TIME    = 6;
parameter GREEN_TIME  = 4;
parameter YELLOW_TIME = 2;
reg [1:0] state;    
reg [2:0] counter;

always @(posedge clk or posedge reset) begin
    if (reset) begin
        state   <= RED_STATE;
        counter <= 0;
    end
    else begin
        case (state)

            RED_STATE: begin
                if (counter == RED_TIME - 1) begin
                    state   <= GREEN_STATE;
                    counter <= 0;           
                end
                else begin
                    counter <= counter + 1; 
                end
            end

            GREEN_STATE: begin
                if (counter == GREEN_TIME - 1) begin
                    state   <= YELLOW_STATE;
                    counter <= 0;
                end
                else begin
                    counter <= counter + 1;
                end
            end

            YELLOW_STATE: begin
                if (counter == YELLOW_TIME - 1) begin
                    state   <= RED_STATE;
                    counter <= 0;
                end
                else begin
                    counter <= counter + 1;
                end
            end

           
            default: begin
                state   <= RED_STATE;
                counter <= 0;
            end

        endcase
    end
end
always @(*) begin
    red    = 0;
    green  = 0;
    yellow = 0;

    case (state)
        RED_STATE:    red    = 1;
        GREEN_STATE:  green  = 1;
        YELLOW_STATE: yellow = 1;
    endcase
end

endmodule

fsm_tb.v
module fsm_tb;
reg  clk, reset;
wire red, green, yellow;
fsm dut (
    .clk    (clk),
    .reset  (reset),
    .red    (red),
    .green  (green),
    .yellow (yellow)
);
initial clk = 1;
always #1 clk = ~clk;
initial begin
    $dumpfile("fsm.vcd");
    $dumpvars(0, fsm_tb);
    reset=1;#10

    reset=0;
    #40$finish;
end
initial begin
    $monitor("Time=%0t | clk=%b reset=%b | RED=%b GREEN=%b YELLOW=%b",
              $time, clk, reset, red, green, yellow);
end
endmodule

fsm.vcd
$date
	Tue Apr 21 14:17:55 2026
$end
$version
	Icarus Verilog
$end
$timescale
	1s
$end
$scope module fsm_tb $end
$var wire 1 ! yellow $end
$var wire 1 " red $end
$var wire 1 # green $end
$var reg 1 $ clk $end
$var reg 1 % reset $end
$scope module dut $end
$var wire 1 $ clk $end
$var wire 1 % reset $end
$var parameter 2 & GREEN_STATE $end
$var parameter 32 ' GREEN_TIME $end
$var parameter 2 ( RED_STATE $end
$var parameter 32 ) RED_TIME $end
$var parameter 2 * YELLOW_STATE $end
$var parameter 32 + YELLOW_TIME $end
$var reg 3 , counter [2:0] $end
$var reg 1 # green $end
$var reg 1 " red $end
$var reg 2 - state [1:0] $end
$var reg 1 ! yellow $end
$upscope $end
$upscope $end
$enddefinitions $end
$comment Show the parameter values. $end
$dumpall
b10 +
b1 *
b110 )
b0 (
b100 '
b10 &
$end
#0
$dumpvars
b0 -
b0 ,
1%
1$
0#
1"
0!
$end
#1
0$
#2
1$
#3
0$
#4
1$
#5
0$
#6
1$
#7
0$
#8
1$
#9
0$
#10
b1 ,
1$
0%
#11
0$
#12
b10 ,
1$
#13
0$
#14
b11 ,
1$
#15
0$
#16
b100 ,
1$
#17
0$
#18
b101 ,
1$
#19
0$
#20
1#
0"
b0 ,
b10 -
1$
#21
0$
#22
b1 ,
1$
#23
0$
#24
b10 ,
1$
#25
0$
#26
b11 ,
1$
#27
0$
#28
1!
0#
b0 ,
b1 -
1$
#29
0$
#30
b1 ,
1$
#31
0$
#32
1"
0!
b0 ,
b0 -
1$
#33
0$
#34
b1 ,
1$
#35
0$
#36
b10 ,
1$
#37
0$
#38
b11 ,
1$
#39
0$
#40
b100 ,
1$
#41
0$
#42
b101 ,
1$
#43
0$
#44
1#
0"
b0 ,
b10 -
1$
#45
0$
#46
b1 ,
1$
#47
0$
#48
b10 ,
1$
#49
0$
#50
b11 ,
1$
